flask_logger/__init__.py
flask_logger/extension.py
Flask_Logger-1.0.4.dist-info/LICENSE.md
Flask_Logger-1.0.4.dist-info/METADATA
Flask_Logger-1.0.4.dist-info/WHEEL
Flask_Logger-1.0.4.dist-info/top_level.txt
Flask_Logger-1.0.4.dist-info/RECORD
