Metadata-Version: 2.1
Name: Flask-Logger
Version: 1.0.4
Summary: Convenience logger for Flask apps
Home-page: https://github.com/bbelyeu/flask-logger
Author: Brad Belyeu
Author-email: bradleylamar@gmail.com
License: MIT
Download-URL: https://github.com/bbelyeu/flask-logger/archive/1.0.4.zip
Keywords: flask,logging,logger,api
Platform: any
Classifier: Environment :: Web Environment
Classifier: Intended Audience :: Developers
Classifier: License :: OSI Approved :: MIT License
Classifier: Operating System :: OS Independent
Classifier: Programming Language :: Python
Classifier: Programming Language :: Python :: 3
Classifier: Topic :: Internet :: WWW/HTTP :: Dynamic Content
Classifier: Topic :: Software Development :: Libraries :: Python Modules
Requires-Dist: Flask
Provides-Extra: sentry
Requires-Dist: sentry-sdk ; extra == 'sentry'
